{
  "$schema": "http://json-schema.org/draft-07/schema#",
  "type": "object",
  "properties": {
    "nameOverride": {
      "type": "string"
    },
    "fullnameOverride": {
      "type": "string"
    },
    "config": {
      "type": "object",
      "properties": {
        "inline": {
          "type": "object"
        }
      }
    },
    "keycloak": {
      "type": "object",
      "properties": {
        "url": {
          "type": "string"
        },
        "realm": {
          "type": "string"
        },
        "clientId": {
          "type": "string"
        }
      }
    },
    "ravnar": {
      "type": "object",
      "properties": {
        "image": {
          "type": "object",
          "properties": {
            "repository": {
              "type": "string"
            },
            "tag": {
              "type": "string"
            }
          }
        },
        "config": {
          "type": "object",
          "properties": {
            "existingConfigMap": {
              "type": "object",
              "properties": {
                "name": {
                  "type": "string"
                }
              }
            }
          }
        },
        "ingress": {
          "type": "object",
          "properties": {
            "enabled": {
              "type": "boolean"
            }
          }
        }
      }
    },
    "backend": {
      "type": "object",
      "properties": {
        "nebariapp": {
          "$ref": "#/definitions/nebariapp"
        }
      },
      "required": ["nebariapp"]
    },
    "frontend": {
      "type": "object",
      "properties": {
        "enabled": {
          "type": "boolean"
        },
        "replicaCount": {
          "type": "integer",
          "minimum": 0
        },
        "podAnnotations": {
          "type": "object"
        },
        "podLabels": {
          "type": "object"
        },
        "image": {
          "type": "object",
          "properties": {
            "repository": {
              "type": "string"
            },
            "tag": {
              "type": "string"
            },
            "pullPolicy": {
              "type": "string",
              "enum": ["IfNotPresent", "Always", "Never"]
            }
          }
        },
        "securityContext": {
          "type": "object",
          "properties": {
            "pod": {
              "type": "object"
            },
            "container": {
              "type": "object"
            }
          }
        },
        "resources": {
          "type": "object",
          "properties": {
            "limits": {
              "type": "object",
              "properties": {
                "cpu": {
                  "type": "string"
                },
                "memory": {
                  "type": "string"
                }
              }
            },
            "requests": {
              "type": "object",
              "properties": {
                "cpu": {
                  "type": "string"
                },
                "memory": {
                  "type": "string"
                }
              }
            }
          }
        },
        "service": {
          "type": "object",
          "properties": {
            "type": {
              "type": "string"
            },
            "port": {
              "type": "integer",
              "minimum": 1,
              "maximum": 65535
            },
            "targetPort": {
              "type": "integer",
              "minimum": 1,
              "maximum": 65535
            }
          }
        },
        "keycloak": {
          "type": "object",
          "properties": {
            "authServerUrl": {
              "type": "string"
            },
            "realm": {
              "type": "string"
            },
            "resource": {
              "type": "string"
            }
          }
        },
        "api": {
          "type": "object",
          "properties": {
            "url": {
              "type": "string"
            }
          }
        },
        "nebariapp": {
          "$ref": "#/definitions/nebariapp"
        }
      }
    }
  },
  "definitions": {
    "nebariapp": {
      "type": "object",
      "properties": {
        "hostname": {
          "type": "string",
          "anyOf": [
            { "maxLength": 0 },
            { "pattern": "^[a-z0-9]([-a-z0-9]*[a-z0-9])?(\\.[a-z0-9]([-a-z0-9]*[a-z0-9])?)*$" }
          ]
        },
        "serviceAccountName": {
          "type": "string",
          "minLength": 1
        },
        "routing": {
          "type": "object",
          "properties": {
            "routes": {
              "type": "array",
              "items": {
                "$ref": "#/definitions/routeMatch"
              }
            },
            "publicRoutes": {
              "type": "array",
              "items": {
                "$ref": "#/definitions/routeMatch"
              }
            },
            "tls": {
              "type": "object",
              "properties": {
                "enabled": {
                  "type": "boolean"
                }
              }
            },
            "annotations": {
              "type": "object",
              "additionalProperties": {
                "type": "string"
              }
            }
          }
        },
        "auth": {
          "type": "object",
          "properties": {
            "enabled": {
              "type": "boolean"
            },
            "provider": {
              "type": "string",
              "enum": ["keycloak", "generic-oidc"]
            },
            "redirectURI": {
              "type": "string"
            },
            "clientSecretRef": {
              "type": "string"
            },
            "scopes": {
              "type": "array",
              "items": {
                "type": "string"
              }
            },
            "groups": {
              "type": "array",
              "items": {
                "type": "string"
              }
            },
            "provisionClient": {
              "type": "boolean"
            },
            "enforceAtGateway": {
              "type": "boolean"
            },
            "forwardAccessToken": {
              "type": "boolean"
            },
            "denyRedirect": {
              "type": "array",
              "items": {
                "$ref": "#/definitions/denyRedirectHeader"
              }
            },
            "issuerURL": {
              "type": "string"
            },
            "spaClient": {
              "type": "object",
              "properties": {
                "enabled": {
                  "type": "boolean"
                },
                "clientId": {
                  "type": "string"
                }
              }
            },
            "deviceFlowClient": {
              "type": "object",
              "properties": {
                "enabled": {
                  "type": "boolean"
                }
              }
            },
            "keycloakConfig": {
              "type": "object",
              "properties": {
                "groups": {
                  "type": "array",
                  "items": {
                    "$ref": "#/definitions/keycloakGroup"
                  }
                },
                "protocolMappers": {
                  "type": "array",
                  "items": {
                    "$ref": "#/definitions/keycloakProtocolMapperConfig"
                  }
                }
              }
            },
            "tokenExchange": {
              "type": "object",
              "properties": {
                "enabled": {
                  "type": "boolean"
                }
              }
            }
          }
        },
        "gateway": {
          "type": "string",
          "enum": ["public", "internal"]
        },
        "landingPage": {
          "type": "object",
          "properties": {
            "enabled": {
              "type": "boolean"
            },
            "displayName": {
              "type": "string",
              "maxLength": 64
            },
            "description": {
              "type": "string",
              "maxLength": 256
            },
            "icon": {
              "type": "string"
            },
            "category": {
              "type": "string"
            },
            "priority": {
              "type": "integer",
              "minimum": 0,
              "maximum": 1000
            },
            "externalUrl": {
              "type": "string"
            },
            "healthCheck": {
              "type": "object",
              "properties": {
                "enabled": {
                  "type": "boolean"
                },
                "path": {
                  "type": "string"
                },
                "port": {
                  "type": "integer",
                  "minimum": 1,
                  "maximum": 65535
                },
                "intervalSeconds": {
                  "type": "integer",
                  "minimum": 10,
                  "maximum": 300
                },
                "timeoutSeconds": {
                  "type": "integer",
                  "minimum": 1,
                  "maximum": 30
                }
              }
            }
          }
        }
      },
      "required": ["hostname"]
    },
    "routeMatch": {
      "type": "object",
      "properties": {
        "pathPrefix": {
          "type": "string",
          "pattern": "^/.*"
        },
        "pathType": {
          "type": "string",
          "enum": ["PathPrefix", "Exact"]
        }
      },
      "required": ["pathPrefix"]
    },
    "denyRedirectHeader": {
      "type": "object",
      "properties": {
        "name": {
          "type": "string",
          "minLength": 1
        },
        "type": {
          "type": "string",
          "enum": ["Exact", "Prefix", "Suffix", "RegularExpression"]
        },
        "value": {
          "type": "string",
          "minLength": 1
        }
      },
      "required": ["name", "value"]
    },
    "keycloakGroup": {
      "type": "object",
      "properties": {
        "name": {
          "type": "string",
          "minLength": 1
        },
        "members": {
          "type": "array",
          "items": {
            "type": "string"
          }
        }
      },
      "required": ["name"]
    },
    "keycloakProtocolMapperConfig": {
      "type": "object",
      "properties": {
        "name": {
          "type": "string",
          "minLength": 1
        },
        "protocolMapper": {
          "type": "string",
          "minLength": 1
        },
        "config": {
          "type": "object",
          "additionalProperties": {
            "type": "string"
          }
        }
      },
      "required": ["name", "protocolMapper"]
    }
  }
}
